{
  "project_info": {
    "project_number": "696129897089",
    "project_id": "prepify-29a66",
    "storage_bucket": "prepify-29a66.appspot.com"
  },
  "client": [
    {
      "client_info": {
        "mobilesdk_app_id": "1:696129897089:android:db97f5c52036baa6698380",
        "android_client_info": {
          "package_name": "com.anonymous.PrepifyMobile"
        }
      },
      "oauth_client": [],
      "api_key": [
        {
          "current_key": "AIzaSyBY3Ta4auwk0fjVIv6hZkDM6dvMnOqKV0k"
        }
      ],
      "services": {
        "appinvite_service": {
          "other_platform_oauth_client": []
        }
      }
    }
  ],
  "configuration_version": "1"
}